{
  "date": "2026-04-15",
  "total_records": 5676,
  "period": "last_90_days",
  "by_neighborhood": {
    "five-points": 487,
    "capitol-hill": 404,
    "civic-center": 277,
    "dia": 274,
    "union-station": 240,
    "central-park": 221,
    "east-colfax": 216,
    "cbd": 186,
    "gateway-green-valley-ranch": 156,
    "lincoln-park": 151,
    "west-colfax": 148,
    "baker": 137,
    "northeast-park-hill": 129,
    "north-capitol-hill": 125,
    "westwood": 118,
    "montbello": 108,
    "college-view-south-platte": 102,
    "city-park-west": 93,
    "hampden": 91,
    "elyria-swansea": 76,
    "villa-park": 74,
    "washington-virginia-vale": 73,
    "ruby-hill": 73,
    "auraria": 71,
    "hampden-south": 62,
    "mar-lee": 62,
    "globeville": 60,
    "cheesman-park": 59,
    "sun-valley": 59,
    "clayton": 55
  },
  "by_offense_type": {
    "criminal-mischief-mtr-veh": 847,
    "criminal-trespassing": 723,
    "criminal-mischief-other": 657,
    "drug-poss-paraphernalia": 434,
    "drug-pcs-other-drug": 342,
    "threats-to-injure": 287,
    "violation-of-court-order": 287,
    "disturbing-the-peace": 231,
    "public-order-crimes-other": 217,
    "weapon-unlawful-discharge-of": 152,
    "violation-of-restraining-order": 123,
    "harassment": 95,
    "police-interference": 93,
    "criminal-mischief-graffiti": 80,
    "drug-opium-or-deriv-sell": 64,
    "sex-off-fail-to-register": 63,
    "weapon-other-viol": 63,
    "drug-methampetamine-possess": 59,
    "weapon-poss-illegal-dangerous": 59,
    "weapon-flourishing": 58
  }
}