{
  "date": "2026-04-28",
  "total_records": 5662,
  "period": "last_90_days",
  "by_neighborhood": {
    "five-points": 491,
    "capitol-hill": 397,
    "dia": 264,
    "civic-center": 261,
    "union-station": 238,
    "central-park": 213,
    "east-colfax": 207,
    "cbd": 185,
    "lincoln-park": 160,
    "west-colfax": 144,
    "gateway-green-valley-ranch": 143,
    "baker": 137,
    "north-capitol-hill": 133,
    "northeast-park-hill": 123,
    "westwood": 120,
    "montbello": 105,
    "college-view-south-platte": 101,
    "city-park-west": 98,
    "hampden": 90,
    "elyria-swansea": 80,
    "washington-virginia-vale": 77,
    "mar-lee": 77,
    "auraria": 76,
    "villa-park": 71,
    "ruby-hill": 69,
    "cheesman-park": 67,
    "clayton": 62,
    "hampden-south": 62,
    "speer": 62,
    "sunnyside": 61
  },
  "by_offense_type": {
    "criminal-mischief-mtr-veh": 812,
    "criminal-trespassing": 751,
    "criminal-mischief-other": 648,
    "drug-poss-paraphernalia": 441,
    "drug-pcs-other-drug": 329,
    "threats-to-injure": 289,
    "violation-of-court-order": 276,
    "disturbing-the-peace": 230,
    "public-order-crimes-other": 230,
    "weapon-unlawful-discharge-of": 160,
    "violation-of-restraining-order": 133,
    "harassment": 96,
    "police-interference": 95,
    "criminal-mischief-graffiti": 79,
    "sex-off-fail-to-register": 69,
    "weapon-poss-illegal-dangerous": 61,
    "drug-opium-or-deriv-sell": 59,
    "police-false-information": 57,
    "weapon-other-viol": 57,
    "weapon-flourishing": 56
  }
}